lwviewv2/__init__.py
lwviewv2/landmark.py
lwviewv2/lw_babel.py
lwviewv2/lw_image.py
lwviewv2/lw_nrrd.py
lwviewv2/lw_view copy.py
lwviewv2/lw_view.py
lwviewv2/util.py
lwviewv2-1.2.5.dist-info/METADATA
lwviewv2-1.2.5.dist-info/WHEEL
lwviewv2-1.2.5.dist-info/top_level.txt
lwviewv2-1.2.5.dist-info/RECORD
