Metadata-Version: 2.1
Name: lwviewv2
Version: 1.2.5
Summary: Viewer of images in python.
Home-page: https://github.com/ReubenDo/lightweight-viewer
Author: Sandy Wells and Reuben Dorent
Author-email: dorent@live.fr
License: MIT
Classifier: Intended Audience :: Science/Research
Classifier: Programming Language :: Python
Classifier: Topic :: Scientific/Engineering
Classifier: Operating System :: Unix
Classifier: Operating System :: MacOS
Requires-Python: >=3.9
Requires-Dist: pynrrd
Requires-Dist: scipy
Requires-Dist: pillow
Requires-Dist: tk
Requires-Dist: numpy
Requires-Dist: nibabel
